allthethings/__init__.py
allthethings/__pkginfo__.py
allthethings/base_convert.py
allthethings/daterange.py
allthethings/dates.py
allthethings/db.py
allthethings/iterables.py
allthethings/ranges.py
allthethings/singleton.py
allthethings/stopwatch.py
tests/__init__.py
tests/test_daterange.py
tests/test_iterables.py
tests/test_ranges.py
allthethings-0.5.0.dist-info/LICENSE
allthethings-0.5.0.dist-info/METADATA
allthethings-0.5.0.dist-info/WHEEL
allthethings-0.5.0.dist-info/top_level.txt
allthethings-0.5.0.dist-info/RECORD
