Metadata-Version: 2.1
Name: allthethings
Version: 0.5.0
Summary: Various utilities
Home-page: https://github.com/scravy/allthethings
Author: Julian Fleischer
Author-email: tirednesscankill@warhog.net
License: UNKNOWN
Platform: UNKNOWN
Classifier: Programming Language :: Python :: 3
Classifier: License :: OSI Approved :: MIT License
Classifier: Operating System :: OS Independent
Requires-Python: >=3.8
